<?xml version="1.0" encoding="UTF-8" standalone="yes"?><Document><name>ValueLayout.OfByte.spec</name><Context><name>class:ValueLayout.OfByte</name><mt>NONE</mt></Context><Context><name>method:withBitAlignment(long)</name><mt>NONE</mt></Context><Context><name>method:withName(java.lang.String)</name><mt>NONE</mt></Context><Context><name>method:withOrder(java.nio.ByteOrder)</name><mt>NONE</mt></Context><Stat><name>ValueLayout.OfByte.spec</name><mt>NONE</mt><Group name="context"><Item name="ADDED" count="0"/><Item name="REMOVED" count="0"/><Item name="CHANGED" count="0"/><Item name="MODIFIED" count="0"/><Item name="MOVED" count="0"/><Item name="MOVED_CHANGED" count="0"/><Item name="JOINT" count="0"/><Item name="SPLIT" count="0"/><Item name="TOTAL" count="4"/></Group><Group name="assertion"><Item name="ADDED" count="0"/><Item name="REMOVED" count="0"/><Item name="CHANGED" count="0"/><Item name="MODIFIED" count="0"/><Item name="MOVED" count="0"/><Item name="MOVED_CHANGED" count="0"/><Item name="JOINT" count="0"/><Item name="SPLIT" count="0"/><Item name="TOTAL" count="0"/></Group></Stat></Document>